[{"name":"Laird Heild","email":"lheild0@indiegogo.com","password":100,"profilePicture":"http://dummyimage.com/215x100.png/dddddd/000000"},
{"name":"Lila Rickaby","email":"lrickaby1@exblog.jp","password":100,"profilePicture":"http://dummyimage.com/242x100.png/5fa2dd/ffffff"},
{"name":"Mab Burtonwood","email":"mburtonwood2@columbia.edu","password":100,"profilePicture":"http://dummyimage.com/135x100.png/cc0000/ffffff"},
{"name":"Sula Dorian","email":"sdorian3@e-recht24.de","password":100,"profilePicture":"http://dummyimage.com/125x100.png/dddddd/000000"},
{"name":"Aldwin Cashley","email":"acashley4@bloglovin.com","password":100,"profilePicture":"http://dummyimage.com/134x100.png/ff4444/ffffff"},
{"name":"Putnem Parriss","email":"pparriss5@shinystat.com","password":100,"profilePicture":"http://dummyimage.com/190x100.png/cc0000/ffffff"},
{"name":"Iorgos Minshall","email":"iminshall6@huffingtonpost.com","password":100,"profilePicture":"http://dummyimage.com/151x100.png/dddddd/000000"},
{"name":"Anatole Ruckledge","email":"aruckledge7@google.com.au","password":100,"profilePicture":"http://dummyimage.com/230x100.png/cc0000/ffffff"},
{"name":"Pearce Pinnijar","email":"ppinnijar8@hubpages.com","password":100,"profilePicture":"http://dummyimage.com/208x100.png/cc0000/ffffff"},
{"name":"Avis Worsfold","email":"aworsfold9@fc2.com","password":100,"profilePicture":"http://dummyimage.com/152x100.png/5fa2dd/ffffff"}]